<?xml version="1.0"?>
<!DOCTYPE hibernate-mapping PUBLIC "-//Hibernate/Hibernate Mapping DTD 3.0//EN" "http://hibernate.sourceforge.net/hibernate-mapping-3.0.dtd">

<hibernate-mapping default-lazy="false" auto-import="false">
	<import class="com.liferay.samplelar.model.SampleLARBooking" />
	<class name="com.liferay.samplelar.model.impl.SampleLARBookingImpl" table="SampleLARBooking">
		<id name="sampleLARBookingId" type="long">
			<generator class="assigned" />
		</id>
		<property name="uuid" type="com.liferay.portal.dao.orm.hibernate.StringType" column="uuid_" />
		<property name="groupId" type="com.liferay.portal.dao.orm.hibernate.LongType" />
		<property name="companyId" type="com.liferay.portal.dao.orm.hibernate.LongType" />
		<property name="userId" type="com.liferay.portal.dao.orm.hibernate.LongType" />
		<property name="userName" type="com.liferay.portal.dao.orm.hibernate.StringType" />
		<property name="createDate" type="org.hibernate.type.TimestampType" />
		<property name="modifiedDate" type="org.hibernate.type.TimestampType" />
		<property name="bookingNumber" type="com.liferay.portal.dao.orm.hibernate.StringType" />
	</class>
</hibernate-mapping>