<?xml version="1.0"?>
<!DOCTYPE plugin-package PUBLIC "-//Liferay//DTD Plugin Package 4.3.0//EN" "http://www.liferay.com/dtd/liferay-plugin-package_4_3_0.dtd">

<plugin-package>
	<name>Greeny blu Theme</name>
	<module-id>liferay/greeny-blu-theme/4.3.2.1/war</module-id>
	<types>
		<type>theme</type>
	</types>
	<tags>
		<tag>oswd</tag>
		<tag>1-column</tag>
		<tag>2-column</tag>
		<tag>3-column</tag>
	</tags>
	<short-description>
        Greeny blue compose of green, black , blue colours. Change the image however you like. But I suggest you replace the image with a greeny picture. The zip has the source code as well with .PSD Photoshop file and the main html/css files.
	</short-description>
	<change-log>
		Adapted to the latest version of Liferay.
	</change-log>
	<page-url>http://www.oswd.org/design/information/id/3696</page-url>
	<author>heartlessg</author>
	<licenses>
		<license osi-approved="true">Unknown</license>
	</licenses>
	<liferay-versions>
		<liferay-version>4.3.2</liferay-version>
	</liferay-versions>
</plugin-package>