<?xml version="1.0"?>

<root available-locales="en_US" default-locale="en_US">
	<dynamic-element name="footer_column_title" type="text">
		<dynamic-content><![CDATA[Footer Column #1]]></dynamic-content>
		<dynamic-element name="column_content" type="textarea">
			<dynamic-content><![CDATA[<ul class="unstyled"><li><a href="#">Link 1</a></li><li><a href="#">Link 2</a></li><li><a href="#">Link 3</a></li><li><a href="#">Link 4</a></li></ul>]]></dynamic-content>
		</dynamic-element>
	</dynamic-element>
	<dynamic-element name="footer_column_title" type="text">
		<dynamic-content><![CDATA[Footer Column #2]]></dynamic-content>
		<dynamic-element name="column_content" type="textarea">
			<dynamic-content><![CDATA[<ul class="unstyled"><li><a href="#">Link 1</a></li><li><a href="#">Link 2</a></li><li><a href="#">Link 3</a></li><li><a href="#">Link 4</a></li></ul>]]></dynamic-content>
		</dynamic-element>
	</dynamic-element>
	<dynamic-element name="footer_column_title" type="text">
		<dynamic-content><![CDATA[Footer Column #3]]></dynamic-content>
		<dynamic-element name="column_content" type="textarea">
			<dynamic-content><![CDATA[<ul class="unstyled"><li><a href="#">Link 1</a></li><li><a href="#">Link 2</a></li><li><a href="#">Link 3</a></li><li><a href="#">Link 4</a></li></ul>]]></dynamic-content>
		</dynamic-element>
	</dynamic-element>
	<dynamic-element name="footer_column_title" type="text">
		<dynamic-content><![CDATA[Footer Column #4]]></dynamic-content>
		<dynamic-element name="column_content" type="textarea">
			<dynamic-content><![CDATA[<ul class="unstyled"><li><a href="#">Link 1</a></li><li><a href="#">Link 2</a></li><li><a href="#">Link 3</a></li><li><a href="#">Link 4</a></li></ul>]]></dynamic-content>
		</dynamic-element>
	</dynamic-element>
	<dynamic-element name="secondary_footer_content" type="textarea">
		<dynamic-content><![CDATA[<div class="powered-by">Powered by <a href="http://www.liferay.com">Liferay</a></div>]]></dynamic-content>
	</dynamic-element>
</root>