<?xml version="1.0" encoding="UTF-8"?>
<!DOCTYPE beans PUBLIC "-//SPRING//DTD BEAN//EN" "http://www.springframework.org/dtd/spring-beans.dtd">

<beans>
	<bean id="com.liferay.twitter.service.FeedLocalService.impl" class="com.liferay.twitter.service.impl.FeedLocalServiceImpl" />
	<bean id="com.liferay.twitter.service.FeedLocalService.transaction" class="org.springframework.transaction.interceptor.TransactionProxyFactoryBean" lazy-init="true">
		<property name="transactionManager">
			<ref bean="liferayTransactionManager" />
		</property>
		<property name="target">
			<ref bean="com.liferay.twitter.service.FeedLocalService.impl" />
		</property>
		<property name="transactionAttributes">
			<props>
				<prop key="add*">PROPAGATION_REQUIRED,-com.liferay.portal.PortalException,-com.liferay.portal.SystemException</prop>
				<prop key="check*">PROPAGATION_REQUIRED,-com.liferay.portal.PortalException,-com.liferay.portal.SystemException</prop>
				<prop key="clear*">PROPAGATION_REQUIRED,-com.liferay.portal.PortalException,-com.liferay.portal.SystemException</prop>
				<prop key="delete*">PROPAGATION_REQUIRED,-com.liferay.portal.PortalException,-com.liferay.portal.SystemException</prop>
				<prop key="set*">PROPAGATION_REQUIRED,-com.liferay.portal.PortalException,-com.liferay.portal.SystemException</prop>
				<prop key="update*">PROPAGATION_REQUIRED,-com.liferay.portal.PortalException,-com.liferay.portal.SystemException</prop>
				<prop key="*">PROPAGATION_SUPPORTS,readOnly</prop>
			</props>
		</property>
	</bean>
	<bean id="com.liferay.twitter.service.FeedLocalService.velocity" class="org.springframework.aop.framework.ProxyFactoryBean" parent="baseVelocityService">
		<property name="target" ref="com.liferay.twitter.service.FeedLocalService.transaction" />
	</bean>
	<bean id="com.liferay.twitter.service.FeedLocalServiceUtil" class="com.liferay.twitter.service.FeedLocalServiceUtil">
		<property name="service" ref="com.liferay.twitter.service.FeedLocalService.transaction" />
	</bean>
	<bean id="com.liferay.twitter.service.persistence.FeedPersistence.impl" class="com.liferay.twitter.service.persistence.FeedPersistenceImpl" parent="basePersistence" />
	<bean id="com.liferay.twitter.service.persistence.FeedPersistence.transaction" parent="com.liferay.twitter.service.persistence.FeedPersistence.impl" />
	<bean id="com.liferay.twitter.service.persistence.FeedUtil" class="com.liferay.twitter.service.persistence.FeedUtil">
		<property name="persistence" ref="com.liferay.twitter.service.persistence.FeedPersistence.impl" />
	</bean>
</beans>