<?xml version="1.0"?>

<model-hints>
	<model name="com.liferay.wsrp.model.WSRPConsumer">
		<field name="uuid" type="String" />
		<field name="wsrpConsumerId" type="long" />
		<field name="companyId" type="long" />
		<field name="createDate" type="Date" />
		<field name="modifiedDate" type="Date" />
		<field name="name" type="String" />
		<field name="url" type="String">
			<hint-collection name="URL" />
		</field>
		<field name="wsdl" type="String">
			<hint-collection name="CLOB" />
		</field>
		<field name="registrationContextString" type="String">
			<hint-collection name="CLOB" />
		</field>
		<field name="registrationPropertiesString" type="String">
			<hint-collection name="TEXTAREA" />
		</field>
		<field name="forwardCookies" type="String">
			<hint name="max-length">255</hint>
		</field>
		<field name="forwardHeaders" type="String">
			<hint name="max-length">255</hint>
		</field>
		<field name="markupCharacterSets" type="String">
			<hint name="max-length">255</hint>
		</field>
		<field name="lastPublishDate" type="Date" />
	</model>
	<model name="com.liferay.wsrp.model.WSRPConsumerPortlet">
		<field name="uuid" type="String" />
		<field name="wsrpConsumerPortletId" type="long" />
		<field name="companyId" type="long" />
		<field name="createDate" type="Date" />
		<field name="modifiedDate" type="Date" />
		<field name="wsrpConsumerId" type="long" />
		<field name="name" type="String" />
		<field name="portletHandle" type="String">
			<hint name="max-length">255</hint>
		</field>
		<field name="lastPublishDate" type="Date" />
	</model>
	<model name="com.liferay.wsrp.model.WSRPProducer">
		<field name="uuid" type="String" />
		<field name="wsrpProducerId" type="long" />
		<field name="groupId" type="long" />
		<field name="companyId" type="long" />
		<field name="createDate" type="Date" />
		<field name="modifiedDate" type="Date" />
		<field name="name" type="String" />
		<field name="version" type="String" />
		<field name="portletIds" type="String">
			<hint-collection name="TEXTAREA" />
		</field>
		<field name="lastPublishDate" type="Date" />
	</model>
</model-hints>