<?xml version="1.0"?>

<javadocs>
	<javadoc>
		<name>TasksEntryAssetRenderer</name>
		<type>com.liferay.tasks.asset.TasksEntryAssetRenderer</type>
		<author><![CDATA[Matthew Kong]]></author>
		<method>
			<name>TasksEntryAssetRenderer</name>
			<param>
				<name>entry</name>
				<type>com.liferay.tasks.model.TasksEntry</type>
				<comment><![CDATA[]]></comment>
			</param>
		</method>
		<method>
			<name>getClassName</name>
			<return>
				<comment><![CDATA[]]></comment>
			</return>
		</method>
		<method>
			<name>getClassPK</name>
			<return>
				<comment><![CDATA[]]></comment>
			</return>
		</method>
		<method>
			<name>getGroupId</name>
			<return>
				<comment><![CDATA[]]></comment>
			</return>
		</method>
		<method>
			<name>getSummary</name>
			<param>
				<name>locale</name>
				<type>java.util.Locale</type>
				<comment><![CDATA[]]></comment>
			</param>
			<return>
				<comment><![CDATA[]]></comment>
			</return>
		</method>
		<method>
			<name>getTitle</name>
			<param>
				<name>locale</name>
				<type>java.util.Locale</type>
				<comment><![CDATA[]]></comment>
			</param>
			<return>
				<comment><![CDATA[]]></comment>
			</return>
		</method>
		<method>
			<name>getURLViewInContext</name>
			<param>
				<name>liferayPortletRequest</name>
				<type>com.liferay.portal.kernel.portlet.LiferayPortletRequest</type>
				<comment><![CDATA[]]></comment>
			</param>
			<param>
				<name>liferayPortletResponse</name>
				<type>com.liferay.portal.kernel.portlet.LiferayPortletResponse</type>
				<comment><![CDATA[]]></comment>
			</param>
			<param>
				<name>noSuchEntryRedirect</name>
				<type>java.lang.String</type>
				<comment><![CDATA[]]></comment>
			</param>
			<return>
				<comment><![CDATA[]]></comment>
			</return>
		</method>
		<method>
			<name>getUserId</name>
			<return>
				<comment><![CDATA[]]></comment>
			</return>
		</method>
		<method>
			<name>getUserName</name>
			<return>
				<comment><![CDATA[]]></comment>
			</return>
		</method>
		<method>
			<name>getUuid</name>
			<return>
				<comment><![CDATA[]]></comment>
			</return>
		</method>
		<method>
			<name>hasViewPermission</name>
			<param>
				<name>permissionChecker</name>
				<type>com.liferay.portal.security.permission.PermissionChecker</type>
				<comment><![CDATA[]]></comment>
			</param>
			<return>
				<comment><![CDATA[]]></comment>
			</return>
		</method>
		<method>
			<name>render</name>
			<param>
				<name>renderRequest</name>
				<type>javax.portlet.RenderRequest</type>
				<comment><![CDATA[]]></comment>
			</param>
			<param>
				<name>renderResponse</name>
				<type>javax.portlet.RenderResponse</type>
				<comment><![CDATA[]]></comment>
			</param>
			<param>
				<name>template</name>
				<type>java.lang.String</type>
				<comment><![CDATA[]]></comment>
			</param>
			<return>
				<comment><![CDATA[]]></comment>
			</return>
		</method>
		<field>
			<name>_entry</name>
		</field>
	</javadoc>
	<javadoc>
		<name>TasksEntryAssetRendererFactory</name>
		<type>com.liferay.tasks.asset.TasksEntryAssetRendererFactory</type>
		<author><![CDATA[Matthew Kong]]></author>
		<method>
			<name>getAssetRenderer</name>
			<param>
				<name>classPK</name>
				<type>long</type>
				<comment><![CDATA[]]></comment>
			</param>
			<param>
				<name>type</name>
				<type>int</type>
				<comment><![CDATA[]]></comment>
			</param>
			<return>
				<comment><![CDATA[]]></comment>
			</return>
			<throws>
				<name>PortalException</name>
				<type>com.liferay.portal.kernel.exception.PortalException</type>
				<comment><![CDATA[]]></comment>
			</throws>
			<throws>
				<name>SystemException</name>
				<type>com.liferay.portal.kernel.exception.SystemException</type>
				<comment><![CDATA[]]></comment>
			</throws>
		</method>
		<method>
			<name>getClassName</name>
			<return>
				<comment><![CDATA[]]></comment>
			</return>
		</method>
		<method>
			<name>getType</name>
			<return>
				<comment><![CDATA[]]></comment>
			</return>
		</method>
		<method>
			<name>hasPermission</name>
			<param>
				<name>permissionChecker</name>
				<type>com.liferay.portal.security.permission.PermissionChecker</type>
				<comment><![CDATA[]]></comment>
			</param>
			<param>
				<name>classPK</name>
				<type>long</type>
				<comment><![CDATA[]]></comment>
			</param>
			<param>
				<name>actionId</name>
				<type>java.lang.String</type>
				<comment><![CDATA[]]></comment>
			</param>
			<return>
				<comment><![CDATA[]]></comment>
			</return>
			<throws>
				<name>Exception</name>
				<type>java.lang.Exception</type>
				<comment><![CDATA[]]></comment>
			</throws>
		</method>
		<method>
			<name>getIconPath</name>
			<param>
				<name>themeDisplay</name>
				<type>com.liferay.portal.theme.ThemeDisplay</type>
				<comment><![CDATA[]]></comment>
			</param>
			<return>
				<comment><![CDATA[]]></comment>
			</return>
		</method>
		<field>
			<name>CLASS_NAME</name>
		</field>
		<field>
			<name>TYPE</name>
		</field>
	</javadoc>
	<javadoc>
		<name>TasksEntryImpl</name>
		<type>com.liferay.tasks.model.impl.TasksEntryImpl</type>
		<author><![CDATA[Ryan Park]]></author>
		<method>
			<name>TasksEntryImpl</name>
		</method>
		<method>
			<name>getAssigneeFullName</name>
			<return>
				<comment><![CDATA[]]></comment>
			</return>
		</method>
		<method>
			<name>getPriorityLabel</name>
			<return>
				<comment><![CDATA[]]></comment>
			</return>
		</method>
		<method>
			<name>getReporterFullName</name>
			<return>
				<comment><![CDATA[]]></comment>
			</return>
		</method>
		<method>
			<name>getStatusLabel</name>
			<return>
				<comment><![CDATA[]]></comment>
			</return>
		</method>
		<method>
			<name>getUserFullName</name>
			<param>
				<name>userId</name>
				<type>long</type>
				<comment><![CDATA[]]></comment>
			</param>
			<return>
				<comment><![CDATA[]]></comment>
			</return>
		</method>
	</javadoc>
	<javadoc>
		<name>TasksUserNotificationHandler</name>
		<type>com.liferay.tasks.notifications.TasksUserNotificationHandler</type>
		<author><![CDATA[Jonathan Lee]]></author>
		<method>
			<name>TasksUserNotificationHandler</name>
		</method>
		<method>
			<name>getBody</name>
			<param>
				<name>userNotificationEvent</name>
				<type>com.liferay.portal.model.UserNotificationEvent</type>
				<comment><![CDATA[]]></comment>
			</param>
			<param>
				<name>serviceContext</name>
				<type>com.liferay.portal.service.ServiceContext</type>
				<comment><![CDATA[]]></comment>
			</param>
			<return>
				<comment><![CDATA[]]></comment>
			</return>
			<throws>
				<name>Exception</name>
				<type>java.lang.Exception</type>
				<comment><![CDATA[]]></comment>
			</throws>
		</method>
		<method>
			<name>getLink</name>
			<param>
				<name>userNotificationEvent</name>
				<type>com.liferay.portal.model.UserNotificationEvent</type>
				<comment><![CDATA[]]></comment>
			</param>
			<param>
				<name>serviceContext</name>
				<type>com.liferay.portal.service.ServiceContext</type>
				<comment><![CDATA[]]></comment>
			</param>
			<return>
				<comment><![CDATA[]]></comment>
			</return>
			<throws>
				<name>Exception</name>
				<type>java.lang.Exception</type>
				<comment><![CDATA[]]></comment>
			</throws>
		</method>
	</javadoc>
	<javadoc>
		<name>TasksPortlet</name>
		<type>com.liferay.tasks.portlet.TasksPortlet</type>
		<author><![CDATA[Ryan Park]]></author>
		<method>
			<name>deleteTasksEntry</name>
			<param>
				<name>actionRequest</name>
				<type>javax.portlet.ActionRequest</type>
				<comment><![CDATA[]]></comment>
			</param>
			<param>
				<name>actionResponse</name>
				<type>javax.portlet.ActionResponse</type>
				<comment><![CDATA[]]></comment>
			</param>
			<throws>
				<name>Exception</name>
				<type>java.lang.Exception</type>
				<comment><![CDATA[]]></comment>
			</throws>
		</method>
		<method>
			<name>processAction</name>
			<param>
				<name>actionRequest</name>
				<type>javax.portlet.ActionRequest</type>
				<comment><![CDATA[]]></comment>
			</param>
			<param>
				<name>actionResponse</name>
				<type>javax.portlet.ActionResponse</type>
				<comment><![CDATA[]]></comment>
			</param>
			<throws>
				<name>IOException</name>
				<type>java.io.IOException</type>
				<comment><![CDATA[]]></comment>
			</throws>
			<throws>
				<name>PortletException</name>
				<type>javax.portlet.PortletException</type>
				<comment><![CDATA[]]></comment>
			</throws>
		</method>
		<method>
			<name>updateMessage</name>
			<param>
				<name>actionRequest</name>
				<type>javax.portlet.ActionRequest</type>
				<comment><![CDATA[]]></comment>
			</param>
			<param>
				<name>actionResponse</name>
				<type>javax.portlet.ActionResponse</type>
				<comment><![CDATA[]]></comment>
			</param>
			<throws>
				<name>Exception</name>
				<type>java.lang.Exception</type>
				<comment><![CDATA[]]></comment>
			</throws>
		</method>
		<method>
			<name>updateTasksEntry</name>
			<param>
				<name>actionRequest</name>
				<type>javax.portlet.ActionRequest</type>
				<comment><![CDATA[]]></comment>
			</param>
			<param>
				<name>actionResponse</name>
				<type>javax.portlet.ActionResponse</type>
				<comment><![CDATA[]]></comment>
			</param>
			<throws>
				<name>Exception</name>
				<type>java.lang.Exception</type>
				<comment><![CDATA[]]></comment>
			</throws>
		</method>
		<method>
			<name>updateTasksEntryStatus</name>
			<param>
				<name>actionRequest</name>
				<type>javax.portlet.ActionRequest</type>
				<comment><![CDATA[]]></comment>
			</param>
			<param>
				<name>actionResponse</name>
				<type>javax.portlet.ActionResponse</type>
				<comment><![CDATA[]]></comment>
			</param>
			<throws>
				<name>Exception</name>
				<type>java.lang.Exception</type>
				<comment><![CDATA[]]></comment>
			</throws>
		</method>
	</javadoc>
	<javadoc>
		<name>TasksEntryLocalServiceImpl</name>
		<type>com.liferay.tasks.service.impl.TasksEntryLocalServiceImpl</type>
		<author><![CDATA[Ryan Park]]></author>
		<author><![CDATA[Jonathan Lee]]></author>
		<method>
			<name>addTasksEntry</name>
			<param>
				<name>userId</name>
				<type>long</type>
				<comment><![CDATA[]]></comment>
			</param>
			<param>
				<name>title</name>
				<type>java.lang.String</type>
				<comment><![CDATA[]]></comment>
			</param>
			<param>
				<name>priority</name>
				<type>int</type>
				<comment><![CDATA[]]></comment>
			</param>
			<param>
				<name>assigneeUserId</name>
				<type>long</type>
				<comment><![CDATA[]]></comment>
			</param>
			<param>
				<name>dueDateMonth</name>
				<type>int</type>
				<comment><![CDATA[]]></comment>
			</param>
			<param>
				<name>dueDateDay</name>
				<type>int</type>
				<comment><![CDATA[]]></comment>
			</param>
			<param>
				<name>dueDateYear</name>
				<type>int</type>
				<comment><![CDATA[]]></comment>
			</param>
			<param>
				<name>dueDateHour</name>
				<type>int</type>
				<comment><![CDATA[]]></comment>
			</param>
			<param>
				<name>dueDateMinute</name>
				<type>int</type>
				<comment><![CDATA[]]></comment>
			</param>
			<param>
				<name>addDueDate</name>
				<type>boolean</type>
				<comment><![CDATA[]]></comment>
			</param>
			<param>
				<name>serviceContext</name>
				<type>com.liferay.portal.service.ServiceContext</type>
				<comment><![CDATA[]]></comment>
			</param>
			<return>
				<comment><![CDATA[]]></comment>
			</return>
			<throws>
				<name>PortalException</name>
				<type>com.liferay.portal.kernel.exception.PortalException</type>
				<comment><![CDATA[]]></comment>
			</throws>
			<throws>
				<name>SystemException</name>
				<type>com.liferay.portal.kernel.exception.SystemException</type>
				<comment><![CDATA[]]></comment>
			</throws>
		</method>
		<method>
			<name>deleteTasksEntry</name>
			<param>
				<name>tasksEntryId</name>
				<type>long</type>
				<comment><![CDATA[]]></comment>
			</param>
			<return>
				<comment><![CDATA[]]></comment>
			</return>
			<throws>
				<name>PortalException</name>
				<type>com.liferay.portal.kernel.exception.PortalException</type>
				<comment><![CDATA[]]></comment>
			</throws>
			<throws>
				<name>SystemException</name>
				<type>com.liferay.portal.kernel.exception.SystemException</type>
				<comment><![CDATA[]]></comment>
			</throws>
		</method>
		<method>
			<name>deleteTasksEntry</name>
			<param>
				<name>tasksEntry</name>
				<type>com.liferay.tasks.model.TasksEntry</type>
				<comment><![CDATA[]]></comment>
			</param>
			<return>
				<comment><![CDATA[]]></comment>
			</return>
			<throws>
				<name>PortalException</name>
				<type>com.liferay.portal.kernel.exception.PortalException</type>
				<comment><![CDATA[]]></comment>
			</throws>
			<throws>
				<name>SystemException</name>
				<type>com.liferay.portal.kernel.exception.SystemException</type>
				<comment><![CDATA[]]></comment>
			</throws>
		</method>
		<method>
			<name>getAssigneeTasksEntries</name>
			<param>
				<name>userId</name>
				<type>long</type>
				<comment><![CDATA[]]></comment>
			</param>
			<param>
				<name>start</name>
				<type>int</type>
				<comment><![CDATA[]]></comment>
			</param>
			<param>
				<name>end</name>
				<type>int</type>
				<comment><![CDATA[]]></comment>
			</param>
			<return>
				<comment><![CDATA[]]></comment>
			</return>
			<throws>
				<name>SystemException</name>
				<type>com.liferay.portal.kernel.exception.SystemException</type>
				<comment><![CDATA[]]></comment>
			</throws>
		</method>
		<method>
			<name>getAssigneeTasksEntriesCount</name>
			<param>
				<name>userId</name>
				<type>long</type>
				<comment><![CDATA[]]></comment>
			</param>
			<return>
				<comment><![CDATA[]]></comment>
			</return>
			<throws>
				<name>SystemException</name>
				<type>com.liferay.portal.kernel.exception.SystemException</type>
				<comment><![CDATA[]]></comment>
			</throws>
		</method>
		<method>
			<name>getGroupAssigneeTasksEntries</name>
			<param>
				<name>groupId</name>
				<type>long</type>
				<comment><![CDATA[]]></comment>
			</param>
			<param>
				<name>userId</name>
				<type>long</type>
				<comment><![CDATA[]]></comment>
			</param>
			<param>
				<name>start</name>
				<type>int</type>
				<comment><![CDATA[]]></comment>
			</param>
			<param>
				<name>end</name>
				<type>int</type>
				<comment><![CDATA[]]></comment>
			</param>
			<return>
				<comment><![CDATA[]]></comment>
			</return>
			<throws>
				<name>SystemException</name>
				<type>com.liferay.portal.kernel.exception.SystemException</type>
				<comment><![CDATA[]]></comment>
			</throws>
		</method>
		<method>
			<name>getGroupAssigneeTasksEntriesCount</name>
			<param>
				<name>groupId</name>
				<type>long</type>
				<comment><![CDATA[]]></comment>
			</param>
			<param>
				<name>userId</name>
				<type>long</type>
				<comment><![CDATA[]]></comment>
			</param>
			<return>
				<comment><![CDATA[]]></comment>
			</return>
			<throws>
				<name>SystemException</name>
				<type>com.liferay.portal.kernel.exception.SystemException</type>
				<comment><![CDATA[]]></comment>
			</throws>
		</method>
		<method>
			<name>getGroupResolverTasksEntries</name>
			<param>
				<name>groupId</name>
				<type>long</type>
				<comment><![CDATA[]]></comment>
			</param>
			<param>
				<name>userId</name>
				<type>long</type>
				<comment><![CDATA[]]></comment>
			</param>
			<param>
				<name>start</name>
				<type>int</type>
				<comment><![CDATA[]]></comment>
			</param>
			<param>
				<name>end</name>
				<type>int</type>
				<comment><![CDATA[]]></comment>
			</param>
			<return>
				<comment><![CDATA[]]></comment>
			</return>
			<throws>
				<name>SystemException</name>
				<type>com.liferay.portal.kernel.exception.SystemException</type>
				<comment><![CDATA[]]></comment>
			</throws>
		</method>
		<method>
			<name>getGroupResolverTasksEntriesCount</name>
			<param>
				<name>groupId</name>
				<type>long</type>
				<comment><![CDATA[]]></comment>
			</param>
			<param>
				<name>userId</name>
				<type>long</type>
				<comment><![CDATA[]]></comment>
			</param>
			<return>
				<comment><![CDATA[]]></comment>
			</return>
			<throws>
				<name>SystemException</name>
				<type>com.liferay.portal.kernel.exception.SystemException</type>
				<comment><![CDATA[]]></comment>
			</throws>
		</method>
		<method>
			<name>getGroupUserTasksEntries</name>
			<param>
				<name>groupId</name>
				<type>long</type>
				<comment><![CDATA[]]></comment>
			</param>
			<param>
				<name>userId</name>
				<type>long</type>
				<comment><![CDATA[]]></comment>
			</param>
			<param>
				<name>start</name>
				<type>int</type>
				<comment><![CDATA[]]></comment>
			</param>
			<param>
				<name>end</name>
				<type>int</type>
				<comment><![CDATA[]]></comment>
			</param>
			<return>
				<comment><![CDATA[]]></comment>
			</return>
			<throws>
				<name>SystemException</name>
				<type>com.liferay.portal.kernel.exception.SystemException</type>
				<comment><![CDATA[]]></comment>
			</throws>
		</method>
		<method>
			<name>getGroupUserTasksEntriesCount</name>
			<param>
				<name>groupId</name>
				<type>long</type>
				<comment><![CDATA[]]></comment>
			</param>
			<param>
				<name>userId</name>
				<type>long</type>
				<comment><![CDATA[]]></comment>
			</param>
			<return>
				<comment><![CDATA[]]></comment>
			</return>
			<throws>
				<name>SystemException</name>
				<type>com.liferay.portal.kernel.exception.SystemException</type>
				<comment><![CDATA[]]></comment>
			</throws>
		</method>
		<method>
			<name>getResolverTasksEntries</name>
			<param>
				<name>userId</name>
				<type>long</type>
				<comment><![CDATA[]]></comment>
			</param>
			<param>
				<name>start</name>
				<type>int</type>
				<comment><![CDATA[]]></comment>
			</param>
			<param>
				<name>end</name>
				<type>int</type>
				<comment><![CDATA[]]></comment>
			</param>
			<return>
				<comment><![CDATA[]]></comment>
			</return>
			<throws>
				<name>SystemException</name>
				<type>com.liferay.portal.kernel.exception.SystemException</type>
				<comment><![CDATA[]]></comment>
			</throws>
		</method>
		<method>
			<name>getResolverTasksEntriesCount</name>
			<param>
				<name>userId</name>
				<type>long</type>
				<comment><![CDATA[]]></comment>
			</param>
			<return>
				<comment><![CDATA[]]></comment>
			</return>
			<throws>
				<name>SystemException</name>
				<type>com.liferay.portal.kernel.exception.SystemException</type>
				<comment><![CDATA[]]></comment>
			</throws>
		</method>
		<method>
			<name>getTasksEntries</name>
			<param>
				<name>groupId</name>
				<type>long</type>
				<comment><![CDATA[]]></comment>
			</param>
			<param>
				<name>start</name>
				<type>int</type>
				<comment><![CDATA[]]></comment>
			</param>
			<param>
				<name>end</name>
				<type>int</type>
				<comment><![CDATA[]]></comment>
			</param>
			<return>
				<comment><![CDATA[]]></comment>
			</return>
			<throws>
				<name>SystemException</name>
				<type>com.liferay.portal.kernel.exception.SystemException</type>
				<comment><![CDATA[]]></comment>
			</throws>
		</method>
		<method>
			<name>getTasksEntries</name>
			<param>
				<name>groupId</name>
				<type>long</type>
				<comment><![CDATA[]]></comment>
			</param>
			<param>
				<name>priority</name>
				<type>int</type>
				<comment><![CDATA[]]></comment>
			</param>
			<param>
				<name>assigneeUserId</name>
				<type>long</type>
				<comment><![CDATA[]]></comment>
			</param>
			<param>
				<name>reporterUserId</name>
				<type>long</type>
				<comment><![CDATA[]]></comment>
			</param>
			<param>
				<name>status</name>
				<type>int</type>
				<comment><![CDATA[]]></comment>
			</param>
			<param>
				<name>assetTagIds</name>
				<type>long[]</type>
				<comment><![CDATA[]]></comment>
			</param>
			<param>
				<name>notAssetTagIds</name>
				<type>long[]</type>
				<comment><![CDATA[]]></comment>
			</param>
			<param>
				<name>start</name>
				<type>int</type>
				<comment><![CDATA[]]></comment>
			</param>
			<param>
				<name>end</name>
				<type>int</type>
				<comment><![CDATA[]]></comment>
			</param>
			<return>
				<comment><![CDATA[]]></comment>
			</return>
			<throws>
				<name>SystemException</name>
				<type>com.liferay.portal.kernel.exception.SystemException</type>
				<comment><![CDATA[]]></comment>
			</throws>
		</method>
		<method>
			<name>getTasksEntriesCount</name>
			<param>
				<name>groupId</name>
				<type>long</type>
				<comment><![CDATA[]]></comment>
			</param>
			<return>
				<comment><![CDATA[]]></comment>
			</return>
			<throws>
				<name>SystemException</name>
				<type>com.liferay.portal.kernel.exception.SystemException</type>
				<comment><![CDATA[]]></comment>
			</throws>
		</method>
		<method>
			<name>getTasksEntriesCount</name>
			<param>
				<name>groupId</name>
				<type>long</type>
				<comment><![CDATA[]]></comment>
			</param>
			<param>
				<name>priority</name>
				<type>int</type>
				<comment><![CDATA[]]></comment>
			</param>
			<param>
				<name>assigneeUserId</name>
				<type>long</type>
				<comment><![CDATA[]]></comment>
			</param>
			<param>
				<name>reporterUserId</name>
				<type>long</type>
				<comment><![CDATA[]]></comment>
			</param>
			<param>
				<name>status</name>
				<type>int</type>
				<comment><![CDATA[]]></comment>
			</param>
			<param>
				<name>tagsEntryIds</name>
				<type>long[]</type>
				<comment><![CDATA[]]></comment>
			</param>
			<param>
				<name>notTagsEntryIds</name>
				<type>long[]</type>
				<comment><![CDATA[]]></comment>
			</param>
			<return>
				<comment><![CDATA[]]></comment>
			</return>
			<throws>
				<name>SystemException</name>
				<type>com.liferay.portal.kernel.exception.SystemException</type>
				<comment><![CDATA[]]></comment>
			</throws>
		</method>
		<method>
			<name>getTasksEntry</name>
			<param>
				<name>tasksEntryId</name>
				<type>long</type>
				<comment><![CDATA[]]></comment>
			</param>
			<return>
				<comment><![CDATA[]]></comment>
			</return>
			<throws>
				<name>PortalException</name>
				<type>com.liferay.portal.kernel.exception.PortalException</type>
				<comment><![CDATA[]]></comment>
			</throws>
			<throws>
				<name>SystemException</name>
				<type>com.liferay.portal.kernel.exception.SystemException</type>
				<comment><![CDATA[]]></comment>
			</throws>
		</method>
		<method>
			<name>getUserTasksEntries</name>
			<param>
				<name>userId</name>
				<type>long</type>
				<comment><![CDATA[]]></comment>
			</param>
			<param>
				<name>start</name>
				<type>int</type>
				<comment><![CDATA[]]></comment>
			</param>
			<param>
				<name>end</name>
				<type>int</type>
				<comment><![CDATA[]]></comment>
			</param>
			<return>
				<comment><![CDATA[]]></comment>
			</return>
			<throws>
				<name>SystemException</name>
				<type>com.liferay.portal.kernel.exception.SystemException</type>
				<comment><![CDATA[]]></comment>
			</throws>
		</method>
		<method>
			<name>getUserTasksEntriesCount</name>
			<param>
				<name>userId</name>
				<type>long</type>
				<comment><![CDATA[]]></comment>
			</param>
			<return>
				<comment><![CDATA[]]></comment>
			</return>
			<throws>
				<name>SystemException</name>
				<type>com.liferay.portal.kernel.exception.SystemException</type>
				<comment><![CDATA[]]></comment>
			</throws>
		</method>
		<method>
			<name>updateAsset</name>
			<param>
				<name>userId</name>
				<type>long</type>
				<comment><![CDATA[]]></comment>
			</param>
			<param>
				<name>tasksEntry</name>
				<type>com.liferay.tasks.model.TasksEntry</type>
				<comment><![CDATA[]]></comment>
			</param>
			<param>
				<name>assetCategoryIds</name>
				<type>long[]</type>
				<comment><![CDATA[]]></comment>
			</param>
			<param>
				<name>assetTagNames</name>
				<type>java.lang.String[]</type>
				<comment><![CDATA[]]></comment>
			</param>
			<throws>
				<name>PortalException</name>
				<type>com.liferay.portal.kernel.exception.PortalException</type>
				<comment><![CDATA[]]></comment>
			</throws>
			<throws>
				<name>SystemException</name>
				<type>com.liferay.portal.kernel.exception.SystemException</type>
				<comment><![CDATA[]]></comment>
			</throws>
		</method>
		<method>
			<name>updateTasksEntry</name>
			<param>
				<name>tasksEntryId</name>
				<type>long</type>
				<comment><![CDATA[]]></comment>
			</param>
			<param>
				<name>title</name>
				<type>java.lang.String</type>
				<comment><![CDATA[]]></comment>
			</param>
			<param>
				<name>priority</name>
				<type>int</type>
				<comment><![CDATA[]]></comment>
			</param>
			<param>
				<name>assigneeUserId</name>
				<type>long</type>
				<comment><![CDATA[]]></comment>
			</param>
			<param>
				<name>resolverUserId</name>
				<type>long</type>
				<comment><![CDATA[]]></comment>
			</param>
			<param>
				<name>dueDateMonth</name>
				<type>int</type>
				<comment><![CDATA[]]></comment>
			</param>
			<param>
				<name>dueDateDay</name>
				<type>int</type>
				<comment><![CDATA[]]></comment>
			</param>
			<param>
				<name>dueDateYear</name>
				<type>int</type>
				<comment><![CDATA[]]></comment>
			</param>
			<param>
				<name>dueDateHour</name>
				<type>int</type>
				<comment><![CDATA[]]></comment>
			</param>
			<param>
				<name>dueDateMinute</name>
				<type>int</type>
				<comment><![CDATA[]]></comment>
			</param>
			<param>
				<name>addDueDate</name>
				<type>boolean</type>
				<comment><![CDATA[]]></comment>
			</param>
			<param>
				<name>status</name>
				<type>int</type>
				<comment><![CDATA[]]></comment>
			</param>
			<param>
				<name>serviceContext</name>
				<type>com.liferay.portal.service.ServiceContext</type>
				<comment><![CDATA[]]></comment>
			</param>
			<return>
				<comment><![CDATA[]]></comment>
			</return>
			<throws>
				<name>PortalException</name>
				<type>com.liferay.portal.kernel.exception.PortalException</type>
				<comment><![CDATA[]]></comment>
			</throws>
			<throws>
				<name>SystemException</name>
				<type>com.liferay.portal.kernel.exception.SystemException</type>
				<comment><![CDATA[]]></comment>
			</throws>
		</method>
		<method>
			<name>updateTasksEntryStatus</name>
			<param>
				<name>tasksEntryId</name>
				<type>long</type>
				<comment><![CDATA[]]></comment>
			</param>
			<param>
				<name>resolverUserId</name>
				<type>long</type>
				<comment><![CDATA[]]></comment>
			</param>
			<param>
				<name>status</name>
				<type>int</type>
				<comment><![CDATA[]]></comment>
			</param>
			<param>
				<name>serviceContext</name>
				<type>com.liferay.portal.service.ServiceContext</type>
				<comment><![CDATA[]]></comment>
			</param>
			<return>
				<comment><![CDATA[]]></comment>
			</return>
			<throws>
				<name>PortalException</name>
				<type>com.liferay.portal.kernel.exception.PortalException</type>
				<comment><![CDATA[]]></comment>
			</throws>
			<throws>
				<name>SystemException</name>
				<type>com.liferay.portal.kernel.exception.SystemException</type>
				<comment><![CDATA[]]></comment>
			</throws>
		</method>
		<method>
			<name>addSocialActivity</name>
			<param>
				<name>status</name>
				<type>int</type>
				<comment><![CDATA[]]></comment>
			</param>
			<param>
				<name>tasksEntry</name>
				<type>com.liferay.tasks.model.TasksEntry</type>
				<comment><![CDATA[]]></comment>
			</param>
			<param>
				<name>serviceContext</name>
				<type>com.liferay.portal.service.ServiceContext</type>
				<comment><![CDATA[]]></comment>
			</param>
			<throws>
				<name>PortalException</name>
				<type>com.liferay.portal.kernel.exception.PortalException</type>
				<comment><![CDATA[]]></comment>
			</throws>
			<throws>
				<name>SystemException</name>
				<type>com.liferay.portal.kernel.exception.SystemException</type>
				<comment><![CDATA[]]></comment>
			</throws>
		</method>
		<method>
			<name>sendNotificationEvent</name>
			<param>
				<name>tasksEntry</name>
				<type>com.liferay.tasks.model.TasksEntry</type>
				<comment><![CDATA[]]></comment>
			</param>
			<param>
				<name>oldStatus</name>
				<type>int</type>
				<comment><![CDATA[]]></comment>
			</param>
			<param>
				<name>oldAssigneeUserId</name>
				<type>long</type>
				<comment><![CDATA[]]></comment>
			</param>
			<param>
				<name>serviceContext</name>
				<type>com.liferay.portal.service.ServiceContext</type>
				<comment><![CDATA[]]></comment>
			</param>
			<throws>
				<name>PortalException</name>
				<type>com.liferay.portal.kernel.exception.PortalException</type>
				<comment><![CDATA[]]></comment>
			</throws>
			<throws>
				<name>SystemException</name>
				<type>com.liferay.portal.kernel.exception.SystemException</type>
				<comment><![CDATA[]]></comment>
			</throws>
		</method>
		<method>
			<name>validate</name>
			<param>
				<name>title</name>
				<type>java.lang.String</type>
				<comment><![CDATA[]]></comment>
			</param>
			<throws>
				<name>PortalException</name>
				<type>com.liferay.portal.kernel.exception.PortalException</type>
				<comment><![CDATA[]]></comment>
			</throws>
		</method>
	</javadoc>
	<javadoc>
		<name>TasksEntryServiceImpl</name>
		<type>com.liferay.tasks.service.impl.TasksEntryServiceImpl</type>
		<author><![CDATA[Ryan Park]]></author>
		<method>
			<name>addTasksEntry</name>
			<param>
				<name>title</name>
				<type>java.lang.String</type>
				<comment><![CDATA[]]></comment>
			</param>
			<param>
				<name>priority</name>
				<type>int</type>
				<comment><![CDATA[]]></comment>
			</param>
			<param>
				<name>assigneeUserId</name>
				<type>long</type>
				<comment><![CDATA[]]></comment>
			</param>
			<param>
				<name>dueDateMonth</name>
				<type>int</type>
				<comment><![CDATA[]]></comment>
			</param>
			<param>
				<name>dueDateDay</name>
				<type>int</type>
				<comment><![CDATA[]]></comment>
			</param>
			<param>
				<name>dueDateYear</name>
				<type>int</type>
				<comment><![CDATA[]]></comment>
			</param>
			<param>
				<name>dueDateHour</name>
				<type>int</type>
				<comment><![CDATA[]]></comment>
			</param>
			<param>
				<name>dueDateMinute</name>
				<type>int</type>
				<comment><![CDATA[]]></comment>
			</param>
			<param>
				<name>neverDue</name>
				<type>boolean</type>
				<comment><![CDATA[]]></comment>
			</param>
			<param>
				<name>serviceContext</name>
				<type>com.liferay.portal.service.ServiceContext</type>
				<comment><![CDATA[]]></comment>
			</param>
			<return>
				<comment><![CDATA[]]></comment>
			</return>
			<throws>
				<name>PortalException</name>
				<type>com.liferay.portal.kernel.exception.PortalException</type>
				<comment><![CDATA[]]></comment>
			</throws>
			<throws>
				<name>SystemException</name>
				<type>com.liferay.portal.kernel.exception.SystemException</type>
				<comment><![CDATA[]]></comment>
			</throws>
		</method>
		<method>
			<name>getTasksEntry</name>
			<param>
				<name>tasksEntryId</name>
				<type>long</type>
				<comment><![CDATA[]]></comment>
			</param>
			<return>
				<comment><![CDATA[]]></comment>
			</return>
			<throws>
				<name>PortalException</name>
				<type>com.liferay.portal.kernel.exception.PortalException</type>
				<comment><![CDATA[]]></comment>
			</throws>
			<throws>
				<name>SystemException</name>
				<type>com.liferay.portal.kernel.exception.SystemException</type>
				<comment><![CDATA[]]></comment>
			</throws>
		</method>
		<method>
			<name>updateTasksEntry</name>
			<param>
				<name>tasksEntryId</name>
				<type>long</type>
				<comment><![CDATA[]]></comment>
			</param>
			<param>
				<name>title</name>
				<type>java.lang.String</type>
				<comment><![CDATA[]]></comment>
			</param>
			<param>
				<name>priority</name>
				<type>int</type>
				<comment><![CDATA[]]></comment>
			</param>
			<param>
				<name>assigneeUserId</name>
				<type>long</type>
				<comment><![CDATA[]]></comment>
			</param>
			<param>
				<name>resolverUserId</name>
				<type>long</type>
				<comment><![CDATA[]]></comment>
			</param>
			<param>
				<name>dueDateMonth</name>
				<type>int</type>
				<comment><![CDATA[]]></comment>
			</param>
			<param>
				<name>dueDateDay</name>
				<type>int</type>
				<comment><![CDATA[]]></comment>
			</param>
			<param>
				<name>dueDateYear</name>
				<type>int</type>
				<comment><![CDATA[]]></comment>
			</param>
			<param>
				<name>dueDateHour</name>
				<type>int</type>
				<comment><![CDATA[]]></comment>
			</param>
			<param>
				<name>dueDateMinute</name>
				<type>int</type>
				<comment><![CDATA[]]></comment>
			</param>
			<param>
				<name>neverDue</name>
				<type>boolean</type>
				<comment><![CDATA[]]></comment>
			</param>
			<param>
				<name>status</name>
				<type>int</type>
				<comment><![CDATA[]]></comment>
			</param>
			<param>
				<name>serviceContext</name>
				<type>com.liferay.portal.service.ServiceContext</type>
				<comment><![CDATA[]]></comment>
			</param>
			<return>
				<comment><![CDATA[]]></comment>
			</return>
			<throws>
				<name>PortalException</name>
				<type>com.liferay.portal.kernel.exception.PortalException</type>
				<comment><![CDATA[]]></comment>
			</throws>
			<throws>
				<name>SystemException</name>
				<type>com.liferay.portal.kernel.exception.SystemException</type>
				<comment><![CDATA[]]></comment>
			</throws>
		</method>
	</javadoc>
	<javadoc>
		<name>TasksEntryFinderImpl</name>
		<type>com.liferay.tasks.service.persistence.TasksEntryFinderImpl</type>
		<author><![CDATA[Ryan Park]]></author>
		<method>
			<name>countByG_P_A_R_S_T_N</name>
			<param>
				<name>groupId</name>
				<type>long</type>
				<comment><![CDATA[]]></comment>
			</param>
			<param>
				<name>priority</name>
				<type>int</type>
				<comment><![CDATA[]]></comment>
			</param>
			<param>
				<name>assigneeUserId</name>
				<type>long</type>
				<comment><![CDATA[]]></comment>
			</param>
			<param>
				<name>reporterUserId</name>
				<type>long</type>
				<comment><![CDATA[]]></comment>
			</param>
			<param>
				<name>status</name>
				<type>int</type>
				<comment><![CDATA[]]></comment>
			</param>
			<param>
				<name>assetTagIds</name>
				<type>long[]</type>
				<comment><![CDATA[]]></comment>
			</param>
			<param>
				<name>notAssetTagIds</name>
				<type>long[]</type>
				<comment><![CDATA[]]></comment>
			</param>
			<return>
				<comment><![CDATA[]]></comment>
			</return>
			<throws>
				<name>SystemException</name>
				<type>com.liferay.portal.kernel.exception.SystemException</type>
				<comment><![CDATA[]]></comment>
			</throws>
		</method>
		<method>
			<name>findByG_P_A_R_S_T_N</name>
			<param>
				<name>groupId</name>
				<type>long</type>
				<comment><![CDATA[]]></comment>
			</param>
			<param>
				<name>priority</name>
				<type>int</type>
				<comment><![CDATA[]]></comment>
			</param>
			<param>
				<name>assigneeUserId</name>
				<type>long</type>
				<comment><![CDATA[]]></comment>
			</param>
			<param>
				<name>reporterUserId</name>
				<type>long</type>
				<comment><![CDATA[]]></comment>
			</param>
			<param>
				<name>status</name>
				<type>int</type>
				<comment><![CDATA[]]></comment>
			</param>
			<param>
				<name>assetTagIds</name>
				<type>long[]</type>
				<comment><![CDATA[]]></comment>
			</param>
			<param>
				<name>notAssetTagIds</name>
				<type>long[]</type>
				<comment><![CDATA[]]></comment>
			</param>
			<param>
				<name>start</name>
				<type>int</type>
				<comment><![CDATA[]]></comment>
			</param>
			<param>
				<name>end</name>
				<type>int</type>
				<comment><![CDATA[]]></comment>
			</param>
			<return>
				<comment><![CDATA[]]></comment>
			</return>
			<throws>
				<name>SystemException</name>
				<type>com.liferay.portal.kernel.exception.SystemException</type>
				<comment><![CDATA[]]></comment>
			</throws>
		</method>
		<method>
			<name>setTagsEntryIds</name>
			<param>
				<name>qPos</name>
				<type>com.liferay.portal.kernel.dao.orm.QueryPos</type>
				<comment><![CDATA[]]></comment>
			</param>
			<param>
				<name>assetTagIds</name>
				<type>long[]</type>
				<comment><![CDATA[]]></comment>
			</param>
		</method>
		<field>
			<name>FIND_BY_C_T</name>
		</field>
	</javadoc>
	<javadoc>
		<name>TasksActivityInterpreter</name>
		<type>com.liferay.tasks.social.TasksActivityInterpreter</type>
		<author><![CDATA[Ryan Park]]></author>
		<method>
			<name>getClassNames</name>
			<return>
				<comment><![CDATA[]]></comment>
			</return>
		</method>
		<method>
			<name>getBody</name>
			<param>
				<name>activity</name>
				<type>com.liferay.portlet.social.model.SocialActivity</type>
				<comment><![CDATA[]]></comment>
			</param>
			<param>
				<name>serviceContext</name>
				<type>com.liferay.portal.service.ServiceContext</type>
				<comment><![CDATA[]]></comment>
			</param>
			<return>
				<comment><![CDATA[]]></comment>
			</return>
			<throws>
				<name>Exception</name>
				<type>java.lang.Exception</type>
				<comment><![CDATA[]]></comment>
			</throws>
		</method>
		<method>
			<name>getLink</name>
			<param>
				<name>activity</name>
				<type>com.liferay.portlet.social.model.SocialActivity</type>
				<comment><![CDATA[]]></comment>
			</param>
			<param>
				<name>serviceContext</name>
				<type>com.liferay.portal.service.ServiceContext</type>
				<comment><![CDATA[]]></comment>
			</param>
			<return>
				<comment><![CDATA[]]></comment>
			</return>
		</method>
		<method>
			<name>getTitleArguments</name>
			<param>
				<name>groupName</name>
				<type>java.lang.String</type>
				<comment><![CDATA[]]></comment>
			</param>
			<param>
				<name>activity</name>
				<type>com.liferay.portlet.social.model.SocialActivity</type>
				<comment><![CDATA[]]></comment>
			</param>
			<param>
				<name>link</name>
				<type>java.lang.String</type>
				<comment><![CDATA[]]></comment>
			</param>
			<param>
				<name>title</name>
				<type>java.lang.String</type>
				<comment><![CDATA[]]></comment>
			</param>
			<param>
				<name>serviceContext</name>
				<type>com.liferay.portal.service.ServiceContext</type>
				<comment><![CDATA[]]></comment>
			</param>
			<return>
				<comment><![CDATA[]]></comment>
			</return>
			<throws>
				<name>Exception</name>
				<type>java.lang.Exception</type>
				<comment><![CDATA[]]></comment>
			</throws>
		</method>
		<method>
			<name>getTitlePattern</name>
			<param>
				<name>groupName</name>
				<type>java.lang.String</type>
				<comment><![CDATA[]]></comment>
			</param>
			<param>
				<name>activity</name>
				<type>com.liferay.portlet.social.model.SocialActivity</type>
				<comment><![CDATA[]]></comment>
			</param>
			<return>
				<comment><![CDATA[]]></comment>
			</return>
		</method>
		<method>
			<name>hasPermissions</name>
			<param>
				<name>permissionChecker</name>
				<type>com.liferay.portal.security.permission.PermissionChecker</type>
				<comment><![CDATA[]]></comment>
			</param>
			<param>
				<name>activity</name>
				<type>com.liferay.portlet.social.model.SocialActivity</type>
				<comment><![CDATA[]]></comment>
			</param>
			<param>
				<name>actionId</name>
				<type>java.lang.String</type>
				<comment><![CDATA[]]></comment>
			</param>
			<param>
				<name>serviceContext</name>
				<type>com.liferay.portal.service.ServiceContext</type>
				<comment><![CDATA[]]></comment>
			</param>
			<return>
				<comment><![CDATA[]]></comment>
			</return>
			<throws>
				<name>Exception</name>
				<type>java.lang.Exception</type>
				<comment><![CDATA[]]></comment>
			</throws>
		</method>
		<field>
			<name>_CLASS_NAMES</name>
		</field>
	</javadoc>
	<javadoc>
		<name>TasksActivityKeys</name>
		<type>com.liferay.tasks.social.TasksActivityKeys</type>
		<author><![CDATA[Ryan Park]]></author>
		<field>
			<name>ADD_ENTRY</name>
		</field>
		<field>
			<name>REOPEN_ENTRY</name>
		</field>
		<field>
			<name>RESOLVE_ENTRY</name>
		</field>
		<field>
			<name>UPDATE_ENTRY</name>
		</field>
	</javadoc>
	<javadoc>
		<name>PortletKeys</name>
		<type>com.liferay.tasks.util.PortletKeys</type>
		<author><![CDATA[Jonathan Lee]]></author>
		<field>
			<name>TASKS</name>
		</field>
		<field>
			<name>UPCOMING_TASKS</name>
		</field>
	</javadoc>
	<javadoc>
		<name>WebKeys</name>
		<type>com.liferay.tasks.util.WebKeys</type>
		<author><![CDATA[Jonathan Lee]]></author>
		<field>
			<name>TASKS_ENTRY</name>
		</field>
	</javadoc>
</javadocs>