<?xml version="1.0"?>

<root available-locales="en_US" default-locale="en_US">
	<dynamic-element name="title" repeatable="false" dataType="string" indexType="" required="false" showLabel="true" type="text" width="25">
		<meta-data locale="en_US">
			<entry name="tip"><![CDATA[]]></entry>
			<entry name="label"><![CDATA[Title]]></entry>
			<entry name="predefinedValue"><![CDATA[]]></entry>
		</meta-data>
	</dynamic-element>
	<dynamic-element name="link" repeatable="false" dataType="string" indexType="" required="false" showLabel="true" type="text" width="25">
		<meta-data locale="en_US">
			<entry name="tip"><![CDATA[]]></entry>
			<entry name="label"><![CDATA[URL Link]]></entry>
			<entry name="predefinedValue"><![CDATA[]]></entry>
		</meta-data>
	</dynamic-element>
	<dynamic-element name="image" repeatable="false" dataType="document-library" indexType="" required="false" showLabel="true" type="ddm-documentlibrary" fieldNamespace="ddm">
		<meta-data locale="en_US">
			<entry name="tip"><![CDATA[]]></entry>
			<entry name="label"><![CDATA[Select Image]]></entry>
			<entry name="predefinedValue"><![CDATA[]]></entry>
		</meta-data>
	</dynamic-element>
	<dynamic-element name="description" repeatable="false" dataType="string" indexType="" required="false" showLabel="true" type="textarea" width="25">
		<meta-data locale="en_US">
			<entry name="tip"><![CDATA[]]></entry>
			<entry name="label"><![CDATA[Description]]></entry>
			<entry name="predefinedValue"><![CDATA[]]></entry>
		</meta-data>
	</dynamic-element>
	<dynamic-element name="content" repeatable="false" dataType="html" indexType="" required="false" showLabel="true" type="ddm-text-html" fieldNamespace="ddm" width="25">
		<meta-data locale="en_US">
			<entry name="tip"><![CDATA[]]></entry>
			<entry name="label"><![CDATA[Content]]></entry>
			<entry name="predefinedValue"><![CDATA[]]></entry>
		</meta-data>
	</dynamic-element>
</root>