<?xml version="1.0"?>

<portlet-app xmlns="http://java.sun.com/xml/ns/portlet/portlet-app_2_0.xsd" xmlns:xsi="http://www.w3.org/2001/XMLSchema-instance" xsi:schemaLocation="http://java.sun.com/xml/ns/portlet/portlet-app_2_0.xsd http://java.sun.com/xml/ns/portlet/portlet-app_2_0.xsd" version="2.0">
	<portlet>
		<portlet-name>1</portlet-name>
		<display-name>1</display-name>
		<portlet-class>
			com.liferay.portlet.oauth.mvc.OAuthApplicationAdminPortlet
		</portlet-class>
		<init-param>
			<name>view-jsp</name>
			<value>/html/admin/view.jsp</value>
		</init-param>
		<init-param>
			<name>config-jsp</name>
			<value>/html/admin/config.jsp</value>
		</init-param>
		<init-param>
			<name>copy-request-parameters</name>
			<value>true</value>
		</init-param>
		<expiration-cache>0</expiration-cache>
		<supports>
			<mime-type>text/html</mime-type>
			<portlet-mode>view</portlet-mode>
			<portlet-mode>config</portlet-mode>
		</supports>
		<resource-bundle>content.Admin</resource-bundle>
		<portlet-info>
			<title>OAUTH ADMINISTRATION</title>
			<short-title>OAUTH ADMIN</short-title>
			<keywords>OAUTH APPLICATION MANAGEMENT</keywords>
		</portlet-info>
		<security-role-ref>
			<role-name>administrator</role-name>
		</security-role-ref>
	</portlet>
	<portlet>
		<portlet-name>2</portlet-name>
		<display-name>2</display-name>
		<portlet-class>
			com.liferay.portlet.oauth.mvc.OAuthApplicationAuthorizationPortlet
		</portlet-class>
		<init-param>
			<name>view-jsp</name>
			<value>/html/authorization/view.jsp</value>
		</init-param>
		<init-param>
			<name>config-jsp</name>
			<value>/html/authorization/config.jsp</value>
		</init-param>
		<init-param>
			<name>copy-request-parameters</name>
			<value>true</value>
		</init-param>
		<expiration-cache>0</expiration-cache>
		<supports>
			<mime-type>text/html</mime-type>
			<portlet-mode>view</portlet-mode>
			<portlet-mode>config</portlet-mode>
		</supports>
		<resource-bundle>content.Authorizations</resource-bundle>
		<portlet-info>
			<title>OAUTH AUTHORIZATIONS</title>
			<short-title>OAUTH AUTHORIZATIONS</short-title>
			<keywords>OAUTH AUTHORIZATIONS MANAGEMENT</keywords>
		</portlet-info>
		<security-role-ref>
			<role-name>administrator</role-name>
		</security-role-ref>
		<security-role-ref>
			<role-name>guest</role-name>
		</security-role-ref>
		<security-role-ref>
			<role-name>power-user</role-name>
		</security-role-ref>
		<security-role-ref>
			<role-name>user</role-name>
		</security-role-ref>
	</portlet>
	<portlet>
		<portlet-name>3</portlet-name>
		<display-name>3</display-name>
		<portlet-class>
			com.liferay.portlet.oauth.mvc.OAuthSimulatorPortlet
		</portlet-class>
		<init-param>
			<name>view-jsp</name>
			<value>/html/simulator/view.jsp</value>
		</init-param>
		<init-param>
			<name>config-jsp</name>
			<value>/html/simulator/config.jsp</value>
		</init-param>
		<init-param>
			<name>copy-request-parameters</name>
			<value>true</value>
		</init-param>
		<expiration-cache>0</expiration-cache>
		<supports>
			<mime-type>text/html</mime-type>
			<portlet-mode>view</portlet-mode>
			<portlet-mode>config</portlet-mode>
		</supports>
		<resource-bundle>content.Simulations</resource-bundle>
		<portlet-info>
			<title>OAUTH SIMULATION</title>
			<short-title>OAUTH SIMULATION</short-title>
			<keywords>OAUTH SIMULATION</keywords>
		</portlet-info>
		<security-role-ref>
			<role-name>administrator</role-name>
		</security-role-ref>
		<security-role-ref>
			<role-name>guest</role-name>
		</security-role-ref>
		<security-role-ref>
			<role-name>power-user</role-name>
		</security-role-ref>
		<security-role-ref>
			<role-name>user</role-name>
		</security-role-ref>
	</portlet>
	<portlet>
		<portlet-name>4</portlet-name>
		<display-name>4</display-name>
		<portlet-class>com.liferay.portlet.oauth.mvc.OAuthAuthorizePortlet</portlet-class>
		<init-param>
			<name>copy-request-parameters</name>
			<value>true</value>
		</init-param>
		<init-param>
			<name>view-jsp</name>
			<value>/html/authorize/view.jsp</value>
		</init-param>
		<expiration-cache>0</expiration-cache>
		<supports>
			<mime-type>text/html</mime-type>
			<portlet-mode>view</portlet-mode>
		</supports>
		<resource-bundle>content.Language</resource-bundle>
		<portlet-info>
			<title>Authorize</title>
			<short-title>Authorize</short-title>
			<keywords>Authorize</keywords>
		</portlet-info>
		<security-role-ref>
			<role-name>administrator</role-name>
		</security-role-ref>
		<security-role-ref>
			<role-name>guest</role-name>
		</security-role-ref>
		<security-role-ref>
			<role-name>power-user</role-name>
		</security-role-ref>
		<security-role-ref>
			<role-name>user</role-name>
		</security-role-ref>
	</portlet>
</portlet-app>